gspatial_tools/__init__.py
gspatial_tools/gspatial_tools.py
gspatial_tools-0.1.0.dist-info/LICENSE
gspatial_tools-0.1.0.dist-info/METADATA
gspatial_tools-0.1.0.dist-info/WHEEL
gspatial_tools-0.1.0.dist-info/top_level.txt
gspatial_tools-0.1.0.dist-info/RECORD
