Metadata-Version: 2.1
Name: gspatial-tools
Version: 0.1.0
Summary: Set of utility tools built on top of Geopandas, Xarray, Rasterio and Rioxarray
Home-page: https://github.com/ambeelabs/gspatial_tools/
Author: Ambee
License: MIT
Keywords: geospatial utilities geopandas rasterio rioxarray xarray
Classifier: Development Status :: 4 - Beta
Classifier: Intended Audience :: Developers
Classifier: License :: OSI Approved :: MIT License
Classifier: Programming Language :: Python :: 3.10
License-File: LICENSE
Requires-Dist: geopandas (>=0.13.2)
Requires-Dist: numpy (>=1.23.5)
Requires-Dist: pandas (>=1.5.3)
Requires-Dist: rasterio (>=1.3.8)
Requires-Dist: rioxarray (>=0.13.3)
Requires-Dist: scikit-learn (>=1.2.0)
Requires-Dist: shapely (>=2.0.1)
